{"path":"/device/identifier/Beats-Studio-(1st-generation)-Pigalle-Edition.html","noAds":true,"frontmatter":{"title":"Beats Studio (1st generation) Pigalle Edition","hideTitle":true,"description":"Information lookup for Beats Studio (1st generation) Pigalle Edition","chartType":"device","widePage":false,"device":[{"name":"Beats Studio (1st generation) Pigalle Edition","identifier":[],"key":"Beats Studio (1st generation) Pigalle Edition","released":"2015-12-11","model":[],"board":[],"type":"Beats Headphones"}],"versionArr":[],"hasFirmwares":{"release":false,"beta":false,"internal":false},"hasFirmwareFilters":false,"grouped":false,"subgroups":[],"imgCount":0,"show":{},"noJb":true,"jbCount":0,"img":{"count":1,"dark":false,"key":"Beats Studio (1st generation) Pigalle Edition"},"deviceFilter":[{"label":"Beats Studio (1st generation) Pigalle Edition","value":"Beats Studio (1st generation) Pigalle Edition"}],"head":[["meta",{"property":"og:image","content":"https://img.appledb.dev/device@256/Beats Studio (1st generation) Pigalle Edition/0.png"}]],"sidebar":false,"editLink":false,"lastUpdated":false,"contributors":false}}