{"path":"/device/identifier/Universal-Dock.html","noAds":true,"frontmatter":{"title":"Universal Dock","hideTitle":true,"description":"Information lookup for Universal Dock","chartType":"device","widePage":false,"device":[{"name":"Universal Dock","identifier":[],"key":"Universal Dock","released":"2007-09-05","model":["A1256"],"board":[],"type":"Accessories","img":{"key":"logo","images":[{"id":"0","dark":true}]}}],"versionArr":[{"osStr":"Accessory Firmware","version":"1.0.2","uniqueBuild":"1.0.2","duplicateVersion":false,"url":"/firmware/Accessory-Firmware/1.0.2.html","preinstalled":[],"signed":[],"beta":false,"rc":false,"devices":["Universal Dock"],"deviceFilterArr":["Universal Dock"],"jailbreakCompatibility":{},"downloads":[],"filteredDownloads":[],"otas":[],"filteredOtas":[],"showSigning":false}],"hasFirmwares":{"release":true,"beta":false,"internal":false},"hasFirmwareFilters":false,"grouped":false,"subgroups":[],"imgCount":0,"show":{},"noJb":true,"jbCount":1,"img":{"key":"logo","images":[{"id":0,"dark":true}]},"deviceFilter":[{"label":"Universal Dock","value":"Universal Dock"}],"head":[],"sidebar":false,"editLink":false,"lastUpdated":false,"contributors":false}}