{"title":{"header":"HomePod Software 15.0 beta 2","subtitle":{"text":"Jun 24, 2021 — <code style=\"background: none; padding-inline: 2px; font-size: 1em;\">19J5288e</code>","tags":[{"text":"Beta","colour":"#ab47bc"}]},"image":{"url":null,"align":"right"}},"sections":[{"title":"Devices","type":"grid","class":"smallTitle","content":[{"title":"HomePod mini","key":"HomePod-mini","subtitle":"Dec 11, 2020","subgroups":[],"links":[],"img":"AudioAccessory5,1","imgFlags":{"internal":true,"dark":false},"icons":[{"class":"fas fa-download","link":"https://updates.cdn-apple.com/2021SummerSeed/patches/071-55304/F11A2BA1-068D-404A-A838-25F1A5EC8405/com_apple_MobileAsset_SoftwareUpdate/5908f18c5b352ac627965e2903baa65938398658.zip"}],"link":"/device/HomePod-mini"},{"title":"HomePod (1st generation)","key":"HomePod-(1st-generation)","subtitle":"Feb 9, 2018","subgroups":[],"links":[],"img":"AudioAccessory1,2","imgFlags":{"internal":true,"dark":false},"icons":[{"class":"fas fa-download","link":"https://updates.cdn-apple.com/2021SummerSeed/patches/071-55323/FA5D807C-7F5B-4B2A-B423-33599CC78CE6/com_apple_MobileAsset_SoftwareUpdate/9562c9064a7cbb8c09a71e47449a2afc7ba5a55b.zip"}],"link":"/device/HomePod-(1st-generation)"}]},{"title":"Jailbreaks","type":"list","class":"smallTitle noListDisc customListDisc","content":[{"text":"palera1n","link":"/jailbreak/palera1n","children":[{"text":"HomePod (1st generation)","link":"/device/identifier/AudioAccessory1,1"}],"showLess":"Hide devices","showMore":"Show devices"}]}]}