{"title":{"header":"HomePod Software 18.2","subtitle":{"text":"Dec 11, 2024 — <code style=\"background: none; padding-inline: 2px; font-size: 1em;\">22K155</code>","tags":[{"text":"Release","colour":"#039be5"}]},"image":{"url":"audioos18","align":"left"}},"sections":[{"title":"Devices","type":"grid","class":"smallTitle","content":[{"title":"HomePod mini","key":"HomePod-mini","subtitle":"Dec 11, 2020","subgroups":[],"links":[],"img":"AudioAccessory5,1","imgFlags":{"internal":true,"dark":false},"icons":[{"class":"fas fa-download","link":"https://updates.cdn-apple.com/2024WinterFCS/fullrestores/072-39470/0DC4617F-09DB-47B4-894D-773D5770C890/AudioAccessory5,1_18.2_22K155_Restore.ipsw"}],"link":"/device/HomePod-mini"},{"title":"HomePod (2nd generation)","key":"HomePod-(2nd-generation)","subtitle":"Feb 3, 2023","subgroups":[],"links":[],"img":"AudioAccessory6,1","imgFlags":{"internal":true,"dark":false},"icons":[{"class":"fas fa-download","link":"https://updates.cdn-apple.com/2024WinterFCS/mobileassets/072-39555/01001711-A130-494B-91D4-E61C190535A4/com_apple_MobileAsset_SoftwareUpdate/df7ae90df5211e4f17c5489ebbaf7a31c975df71b437552582a2205ff9d5621c.aea"}],"link":"/device/HomePod-(2nd-generation)"},{"title":"HomePod (1st generation)","key":"AudioAccessory1,1","subtitle":"Feb 9, 2018","subgroups":[],"links":[],"img":"AudioAccessory1,1","imgFlags":{"internal":true,"dark":false},"icons":[{"class":"fas fa-download","link":"https://updates.cdn-apple.com/2024WinterFCS/patches/072-39585/A47FE448-7879-4491-83AA-515CF43CC754/com_apple_MobileAsset_SoftwareUpdate/cf220dbab38bb43fd2dbf4f0010d04f1bc7e90fe.zip"}],"link":"/device/identifier/AudioAccessory1,1"}]}]}