{"title":{"header":"iCloud (Windows) 5.2.2.87","subtitle":{"text":"Jul 18, 2016","tags":[{"text":"Release","colour":"#039be5"}]},"image":{"url":null,"align":"right"}},"sections":[{"type":"buttons","class":"wrap","content":[{"text":"exe (129.5 MB)","key":"iCloud (Windows)","link":"https://download.info.apple.com/Mac_OS_X/031-64889-20160718-E85BB333-494F-11E6-A444-EFCFCF9F5A9B/iCloudSetup.exe","icon":"fas fa-download","type":"exe","size":129500472}]},{"title":"Devices","type":"grid","class":"smallTitle","content":[{"title":"iCloud (Windows)","key":"iCloud (Windows)","subtitle":"Nov 29, 2011","subgroups":[],"links":[],"img":"iCloud (Windows)","imgFlags":{"internal":true,"dark":false},"icons":[],"link":"/device/identifier/iCloud-(Windows)","singleDownload":{"text":"exe (129.5 MB)","key":"iCloud (Windows)","link":"https://download.info.apple.com/Mac_OS_X/031-64889-20160718-E85BB333-494F-11E6-A444-EFCFCF9F5A9B/iCloudSetup.exe","icon":"fas fa-download","type":"exe","size":129500472}}]}]}