{"title":{"header":"iCloud (Windows) 7.20.0.17","subtitle":{"text":"Aug 10, 2020","tags":[{"text":"Release","colour":"#039be5"}]},"image":{"url":null,"align":"right"}},"sections":[{"type":"buttons","class":"wrap","content":[{"text":"exe (161.1 MB)","key":"iCloud (Windows)","link":"https://updates.cdn-apple.com/2020/windows/061-97489-20200728-49EF1218-D0FD-11EA-808A-86ABB27EFCA1/iCloudSetup.exe","icon":"fas fa-download","type":"exe","size":161117496}]},{"title":"Devices","type":"grid","class":"smallTitle","content":[{"title":"iCloud (Windows)","key":"iCloud (Windows)","subtitle":"Nov 29, 2011","subgroups":[],"links":[],"img":"iCloud (Windows)","imgFlags":{"internal":true,"dark":false},"icons":[],"link":"/device/identifier/iCloud-(Windows)","singleDownload":{"text":"exe (161.1 MB)","key":"iCloud (Windows)","link":"https://updates.cdn-apple.com/2020/windows/061-97489-20200728-49EF1218-D0FD-11EA-808A-86ABB27EFCA1/iCloudSetup.exe","icon":"fas fa-download","type":"exe","size":161117496}}]}]}