{"title":{"header":"iCloud Passwords (Firefox) 3.1.31","subtitle":{"text":"Nov 4, 2025","tags":[{"text":"Release","colour":"#039be5"}]},"image":{"url":null,"align":"right","images":[]}},"sections":[{"type":"buttons","class":"wrap","content":[{"text":"xpi (308.5 KB)","key":"iCloud Passwords (Firefox)","link":"https://addons.mozilla.org/firefox/downloads/file/4607938/icloud_passwords-3.1.31.xpi","icon":"fas fa-fw fa-download","type":"xpi","size":308485,"active":true}]},{"title":"Devices","type":"grid","class":"smallTitle","content":[{"title":"iCloud Passwords (Firefox)","key":"iCloud Passwords (Firefox)","subtitle":"Nov 19, 2024","subgroups":[],"links":[],"img":"iCloud Passwords (Firefox)","imgFlags":{"internal":true,"images":[{"id":0,"dark":false}]},"icons":[],"link":"/device/identifier/iCloud-Passwords-(Firefox)","singleDownload":{"text":"xpi (308.5 KB)","key":"iCloud Passwords (Firefox)","link":"https://addons.mozilla.org/firefox/downloads/file/4607938/icloud_passwords-3.1.31.xpi","icon":"fas fa-fw fa-download","type":"xpi","size":308485,"active":true}}]}]}