{"title":{"header":"Icon Composer 1.0 beta 2","subtitle":{"text":"Jun 24, 2025","tags":[{"text":"Beta","colour":"#ab47bc"}]},"image":{"url":null,"align":"right","images":[]}},"sections":[{"type":"buttons","class":"wrap","content":[{"text":"DMG (23.4 MB)","key":"Icon Composer","link":"https://developer.apple.com/download/files/icon-composer.dmg","icon":"fas fa-fw fa-download","type":"dmg","size":23390589,"active":false}]},{"title":"Devices","type":"grid","class":"smallTitle","content":[{"title":"Icon Composer","key":"Icon Composer","subtitle":"Jun 9, 2025","subgroups":[],"links":[],"img":"logo","imgFlags":{"internal":true,"images":[{"id":"0","dark":true}]},"icons":[],"link":"/device/identifier/Icon-Composer","singleDownload":{"text":"DMG (23.4 MB)","key":"Icon Composer","link":"https://developer.apple.com/download/files/icon-composer.dmg","icon":"fas fa-fw fa-download","type":"dmg","size":23390589,"active":false}}]}]}