{"title":{"header":"iOS 14.3","subtitle":{"text":"<code style=\"background: none; padding-inline: 2px; font-size: 1em;\">18C57</code>","tags":[{"text":"Internal","colour":"#f0ad05"}]},"image":{"url":"ios14","align":"left"}},"sections":[{"title":"Devices","type":"grid","class":"smallTitle","content":[{"title":"iPhone 12 Pro","key":"iPhone13,3","subtitle":"Oct 23, 2020","subgroups":[],"links":[],"img":"iPhone13,3","imgFlags":{"internal":true,"dark":true},"icons":[],"link":"/device/identifier/iPhone13,3"}]}]}