{"title":{"header":"iOS 9.2 beta 4","subtitle":{"text":"Nov 18, 2015 — <code style=\"background: none; padding-inline: 2px; font-size: 1em;\">13C75</code>","tags":[{"text":"Beta","colour":"#ab47bc"}]},"image":{"url":"ios9","align":"left"}},"sections":[{"title":"Devices","type":"grid","class":"smallTitle","content":[{"title":"iPod touch (6th generation)","key":"iPod7,1","subtitle":"Jul 15, 2015","subgroups":[],"links":[{"text":"IPSW","key":"iPod7,1","link":"http://adcdownload.apple.com/iOS/iOS_9.2_beta_4/iOS_9.2_beta_4__iPod_touch_6th_generation__13C75.zip","icon":"fas fa-download","type":"ipsw","size":1842478126}],"img":"iPod7,1","imgFlags":{"internal":true,"dark":false},"icons":[],"link":"/device/identifier/iPod7,1"},{"title":"iPod touch (5th generation)","key":"iPod5,1","subtitle":"Oct 11, 2012","subgroups":[],"links":[{"text":"IPSW","key":"iPod5,1","link":"http://adcdownload.apple.com/iOS/iOS_9.2_beta_4/iOS_9.2_beta_4__iPod_touch_5th_generation__13C75.zip","icon":"fas fa-download","type":"ipsw","size":1579055234}],"img":"iPod5,1","imgFlags":{"internal":true,"dark":false},"icons":[],"link":"/device/identifier/iPod5,1"},{"title":"iPhone 6s","key":"iPhone-6s-series","subtitle":"Sep 25, 2015","subgroups":[{"name":"iPhone 6s","type":"iPhone","order":0,"devices":["iPhone8,1"]},{"name":"iPhone 6s Plus","type":"iPhone","order":1,"devices":["iPhone8,2"]}],"links":[{"text":"iPhone 6s Plus","key":"iPhone8,2","link":"http://adcdownload.apple.com/iOS/iOS_9.2_beta_4/iOS_9.2_beta_4__iPhone_6s_Plus__13C75.zip","icon":"fas fa-download","type":"ipsw","size":2382945535},{"text":"iPhone 6s","key":"iPhone8,1","link":"http://adcdownload.apple.com/iOS/iOS_9.2_beta_4/iOS_9.2_beta_4__iPhone_6s__13C75.zip","icon":"fas fa-download","type":"ipsw","size":2149522217}],"img":"iPhone8,2","imgFlags":{"internal":true,"dark":false},"icons":[],"link":"/device/iPhone-6s-series"},{"title":"iPhone 6","key":"iPhone-6-series","subtitle":"Sep 19, 2014","subgroups":[{"name":"iPhone 6","type":"iPhone","order":0,"devices":["iPhone7,2"]},{"name":"iPhone 6 Plus","type":"iPhone","order":1,"devices":["iPhone7,1"]}],"links":[{"text":"iPhone 6 Plus","key":"iPhone7,1","link":"http://adcdownload.apple.com/iOS/iOS_9.2_beta_4/iOS_9.2_beta_4__iPhone_6_Plus__13C75.zip","icon":"fas fa-download","type":"ipsw","size":2196420917},{"text":"iPhone 6","key":"iPhone7,2","link":"http://adcdownload.apple.com/iOS/iOS_9.2_beta_4/iOS_9.2_beta_4__iPhone_6__13C75.zip","icon":"fas fa-download","type":"ipsw","size":1975395381}],"img":"iPhone7,2","imgFlags":{"internal":true,"dark":false},"icons":[],"link":"/device/iPhone-6-series"},{"title":"iPhone 5s","key":"iPhone-5s","subtitle":"Sep 20, 2013","subgroups":[],"links":[{"text":"iPhone 5s (GSM)","key":"iPhone6,1","link":"http://adcdownload.apple.com/iOS/iOS_9.2_beta_4/iOS_9.2_beta_4__iPhone_5s_Model_A1453_A1533__13C75.zip","icon":"fas fa-download","type":"ipsw","size":1948218879},{"text":"iPhone 5s (CDMA)","key":"iPhone6,2","link":"http://adcdownload.apple.com/iOS/iOS_9.2_beta_4/iOS_9.2_beta_4__iPhone_5s_Model_A1457_A1518_A1528_A1530__13C75.zip","icon":"fas fa-download","type":"ipsw","size":1946194950}],"img":"iPhone6,2","imgFlags":{"internal":true,"dark":false},"icons":[],"link":"/device/iPhone-5s"},{"title":"iPhone 5c","key":"iPhone-5c","subtitle":"Sep 20, 2013","subgroups":[],"links":[{"text":"iPhone 5c (GSM)","key":"iPhone5,3","link":"http://adcdownload.apple.com/iOS/iOS_9.2_beta_4/iOS_9.2_beta_4__iPhone_5c_Model_A1456_A1532__13C75.zip","icon":"fas fa-download","type":"ipsw","size":1677566213},{"text":"iPhone 5c (CDMA)","key":"iPhone5,4","link":"http://adcdownload.apple.com/iOS/iOS_9.2_beta_4/iOS_9.2_beta_4__iPhone_5c_Model_A1507_A1516_A1526_A1529__13C75.zip","icon":"fas fa-download","type":"ipsw","size":1675247743}],"img":"iPhone5,4","imgFlags":{"internal":true,"dark":false},"icons":[],"link":"/device/iPhone-5c"},{"title":"iPhone 5","key":"iPhone-5","subtitle":"Sep 21, 2012","subgroups":[],"links":[{"text":"iPhone 5 (GSM)","key":"iPhone5,1","link":"http://adcdownload.apple.com/iOS/iOS_9.2_beta_4/iOS_9.2_beta_4__iPhone_5_Model_A1428__13C75.zip","icon":"fas fa-download","type":"ipsw","size":1668038537},{"text":"iPhone 5 (CDMA)","key":"iPhone5,2","link":"http://adcdownload.apple.com/iOS/iOS_9.2_beta_4/iOS_9.2_beta_4__iPhone_5_Model_A1429__13C75.zip","icon":"fas fa-download","type":"ipsw","size":1668701953}],"img":"iPhone5,2","imgFlags":{"internal":true,"dark":false},"icons":[],"link":"/device/iPhone-5"},{"title":"iPhone 4S","key":"iPhone4,1","subtitle":"Oct 14, 2011","subgroups":[],"links":[{"text":"IPSW","key":"iPhone4,1","link":"http://adcdownload.apple.com/iOS/iOS_9.2_beta_4/iOS_9.2_beta_4__iPhone_4s__13C75.zip","icon":"fas fa-download","type":"ipsw","size":1585524263}],"img":"iPhone4,1","imgFlags":{"internal":true,"dark":false},"icons":[],"link":"/device/identifier/iPhone4,1"},{"title":"iPad mini 4","key":"iPad-mini-4","subtitle":"Sep 9, 2015","subgroups":[],"links":[{"text":"iPad mini 4 Wi-Fi + Cellular","key":"iPad5,2","link":"http://appldnld.apple.com/ios9.2seed/031-32811-20151118-76769D52-8CB9-11E5-97A4-08598B8BECEB/com_apple_MobileAsset_SoftwareUpdate/5e2782f5905f5c629194610f6d2e86b1713d19bb.zip","icon":"fas fa-download","type":"ota","size":1486427749},{"text":"iPad mini 4 Wi-Fi","key":"iPad5,1","link":"http://appldnld.apple.com/ios9.2seed/031-32753-20151118-92C33066-8CB8-11E5-97D3-71558B8BECEB/com_apple_MobileAsset_SoftwareUpdate/1253f56238a15a2f65386f3d496b1b68bf3fd995.zip","icon":"fas fa-download","type":"ota","size":1432679594}],"img":"iPad5,2","imgFlags":{"internal":true,"dark":false},"icons":[],"link":"/device/iPad-mini-4"},{"title":"iPad mini 3","key":"iPad-mini-3","subtitle":"Oct 22, 2014","subgroups":[],"links":[{"text":"iPad mini 3 Wi-Fi + Cellular (TD-LTE)","key":"iPad4,9","link":"http://adcdownload.apple.com/iOS/iOS_9.2_beta_4/iOS_9.2_beta_4__iPad_mini_3_Model_A1601__13C75.zip","icon":"fas fa-download","type":"ipsw","size":1985209889},{"text":"iPad mini 3 Wi-Fi + Cellular","key":"iPad4,8","link":"http://adcdownload.apple.com/iOS/iOS_9.2_beta_4/iOS_9.2_beta_4__iPad_mini_3_Model_A1600__13C75.zip","icon":"fas fa-download","type":"ipsw","size":1985514268},{"text":"iPad mini 3 Wi-Fi","key":"iPad4,7","link":"http://adcdownload.apple.com/iOS/iOS_9.2_beta_4/iOS_9.2_beta_4__iPad_mini_3_Model_A1599__13C75.zip","icon":"fas fa-download","type":"ipsw","size":1937398593}],"img":"iPad4,9","imgFlags":{"internal":true,"dark":false},"icons":[],"link":"/device/iPad-mini-3"},{"title":"iPad mini 2","key":"iPad-mini-2","subtitle":"Nov 12, 2013","subgroups":[],"links":[{"text":"iPad mini 2 Wi-Fi + Cellular","key":"iPad4,5","link":"http://adcdownload.apple.com/iOS/iOS_9.2_beta_4/iOS_9.2_beta_4__iPad_mini_2_Model_A1490__13C75.zip","icon":"fas fa-download","type":"ipsw","size":1978324031},{"text":"iPad mini 2 Wi-Fi","key":"iPad4,4","link":"http://adcdownload.apple.com/iOS/iOS_9.2_beta_4/iOS_9.2_beta_4__iPad_mini_2_Model_A1489__13C75.zip","icon":"fas fa-download","type":"ipsw","size":1927659247},{"text":"iPad mini 2 Wi-Fi + Cellular (TD-LTE)","key":"iPad4,6","link":"http://adcdownload.apple.com/iOS/iOS_9.2_beta_4/iOS_9.2_beta_4__iPad_mini_2_Model_A1491__13C75.zip","icon":"fas fa-download","type":"ipsw","size":1974820704}],"img":"iPad4,6","imgFlags":{"internal":true,"dark":false},"icons":[],"link":"/device/iPad-mini-2"},{"title":"iPad mini","key":"iPad-mini","subtitle":"Nov 2, 2012","subgroups":[],"links":[{"text":"iPad mini Wi-Fi + Cellular (MM)","key":"iPad2,7","link":"http://adcdownload.apple.com/iOS/iOS_9.2_beta_4/iOS_9.2_beta_4__iPad_mini_Model_A1455__13C75.zip","icon":"fas fa-download","type":"ipsw","size":1555885839},{"text":"iPad mini Wi-Fi + Cellular","key":"iPad2,6","link":"http://adcdownload.apple.com/iOS/iOS_9.2_beta_4/iOS_9.2_beta_4__iPad_mini_Model_A1454__13C75.zip","icon":"fas fa-download","type":"ipsw","size":1553626473},{"text":"iPad mini Wi-Fi","key":"iPad2,5","link":"http://adcdownload.apple.com/iOS/iOS_9.2_beta_4/iOS_9.2_beta_4__iPad_mini_Model_A1432__13C75.zip","icon":"fas fa-download","type":"ipsw","size":1513390801}],"img":"iPad2,7","imgFlags":{"internal":true,"dark":false},"icons":[],"link":"/device/iPad-mini"},{"title":"iPad Pro (12.9-inch) (1st generation)","key":"iPad-Pro-(12.9-inch)-(1st-generation)","subtitle":"Nov 11, 2015","subgroups":[],"links":[{"text":"iPad Pro (12.9-inch) (1st generation) Wi-Fi + Cellular","key":"iPad6,8","link":"https://secure-appldnld.apple.com/ios9.2seed/031-32774-20151118-92C766B8-8CB8-11E5-8300-83558B8BECEB/com_apple_MobileAsset_SoftwareUpdate/a38a96e9900e7e9097742e4564f476e0f62be010.zip","icon":"fas fa-download","type":"ota","size":1609623149},{"text":"iPad Pro (12.9-inch) (1st generation) Wi-Fi","key":"iPad6,7","link":"https://secure-appldnld.apple.com/ios9.2seed/031-32807-20151118-5E8B5ACA-8CB9-11E5-9FD8-45588B8BECEB/com_apple_MobileAsset_SoftwareUpdate/5ee5a91bcd9993660d7147265f072402c01c5056.zip","icon":"fas fa-download","type":"ota","size":1557461725}],"img":"iPad6,8","imgFlags":{"internal":true,"dark":false},"icons":[],"link":"/device/iPad-Pro-(12.9-inch)-(1st-generation)"},{"title":"iPad Air 2","key":"iPad-Air-2","subtitle":"Oct 22, 2014","subgroups":[],"links":[{"text":"iPad Air 2 Wi-Fi + Cellular","key":"iPad5,4","link":"http://adcdownload.apple.com/iOS/iOS_9.2_beta_4/iOS_9.2_beta_4__iPad_Air_2_Model_A1567__13C75.zip","icon":"fas fa-download","type":"ipsw","size":1997251778},{"text":"iPad Air 2 Wi-Fi","key":"iPad5,3","link":"http://adcdownload.apple.com/iOS/iOS_9.2_beta_4/iOS_9.2_beta_4__iPad_Air_2_Model_A1566__13C75.zip","icon":"fas fa-download","type":"ipsw","size":1942573253}],"img":"iPad5,4","imgFlags":{"internal":true,"dark":false},"icons":[],"link":"/device/iPad-Air-2"},{"title":"iPad Air","key":"iPad-Air","subtitle":"Nov 1, 2013","subgroups":[],"links":[{"text":"iPad Air Wi-Fi + Cellular","key":"iPad4,2","link":"http://adcdownload.apple.com/iOS/iOS_9.2_beta_4/iOS_9.2_beta_4__iPad_Air_Model_A1475__13C75.zip","icon":"fas fa-download","type":"ipsw","size":1975096377},{"text":"iPad Air Wi-Fi","key":"iPad4,1","link":"http://adcdownload.apple.com/iOS/iOS_9.2_beta_4/iOS_9.2_beta_4__iPad_Air_Model_A1474__13C75.zip","icon":"fas fa-download","type":"ipsw","size":1928425075},{"text":"iPad Air Wi-Fi + Cellular (TD-LTE)","key":"iPad4,3","link":"http://adcdownload.apple.com/iOS/iOS_9.2_beta_4/iOS_9.2_beta_4__iPad_Air_Model_A1476__13C75.zip","icon":"fas fa-download","type":"ipsw","size":1974752505}],"img":"iPad4,3","imgFlags":{"internal":true,"dark":false},"icons":[],"link":"/device/iPad-Air"},{"title":"iPad (4th generation)","key":"iPad-(4th-generation)","subtitle":"Nov 2, 2012","subgroups":[],"links":[{"text":"iPad (4th generation) Wi-Fi + Cellular (MM)","key":"iPad3,6","link":"http://adcdownload.apple.com/iOS/iOS_9.2_beta_4/iOS_9.2_beta_4__iPad_4th_generation_Model_A1460__13C75.zip","icon":"fas fa-download","type":"ipsw","size":1704052926},{"text":"iPad (4th generation) Wi-Fi + Cellular","key":"iPad3,5","link":"http://adcdownload.apple.com/iOS/iOS_9.2_beta_4/iOS_9.2_beta_4__iPad_4th_generation_Model_A1459__13C75.zip","icon":"fas fa-download","type":"ipsw","size":1701931825},{"text":"iPad (4th generation) Wi-Fi","key":"iPad3,4","link":"http://adcdownload.apple.com/iOS/iOS_9.2_beta_4/iOS_9.2_beta_4__iPad_4th_generation_Model_A1458__13C75.zip","icon":"fas fa-download","type":"ipsw","size":1662064978}],"img":"iPad3,6","imgFlags":{"internal":true,"dark":false},"icons":[],"link":"/device/iPad-(4th-generation)"},{"title":"iPad (3rd generation)","key":"iPad-(3rd-generation)","subtitle":"Mar 16, 2012","subgroups":[],"links":[{"text":"iPad (3rd generation) Wi-Fi + Cellular (VZ)","key":"iPad3,2","link":"http://adcdownload.apple.com/iOS/iOS_9.2_beta_4/iOS_9.2_beta_4__iPad_WiFi__Cellular_model_for_Verizon__13C75.zip","icon":"fas fa-download","type":"ipsw","size":1674756979},{"text":"iPad (3rd generation) Wi-Fi + Cellular","key":"iPad3,3","link":"http://adcdownload.apple.com/iOS/iOS_9.2_beta_4/iOS_9.2_beta_4__iPad_WiFi__Cellular_model_for_ATT__13C75.zip","icon":"fas fa-download","type":"ipsw","size":1674489365},{"text":"iPad (3rd generation) Wi-Fi","key":"iPad3,1","link":"http://adcdownload.apple.com/iOS/iOS_9.2_beta_4/iOS_9.2_beta_4__iPad_WiFi_3rd_generation__13C75.zip","icon":"fas fa-download","type":"ipsw","size":1642729805}],"img":"iPad3,3","imgFlags":{"internal":true,"dark":false},"icons":[],"link":"/device/iPad-(3rd-generation)"},{"title":"iPad 2","key":"iPad-2","subtitle":"Mar 11, 2011","subgroups":[],"links":[{"text":"iPad 2 Wi-Fi + 3G (GSM)","key":"iPad2,2","link":"http://adcdownload.apple.com/iOS/iOS_9.2_beta_4/iOS_9.2_beta_4__iPad_2_WiFi__3G_GSM__13C75.zip","icon":"fas fa-download","type":"ipsw","size":1412725063},{"text":"iPad 2 Wi-Fi + 3G (CDMA)","key":"iPad2,3","link":"http://adcdownload.apple.com/iOS/iOS_9.2_beta_4/iOS_9.2_beta_4__iPad_2_WiFi__3G_CDMA__13C75.zip","icon":"fas fa-download","type":"ipsw","size":1410454259},{"text":"iPad 2 Wi-Fi","key":"iPad2,1","link":"http://adcdownload.apple.com/iOS/iOS_9.2_beta_4/iOS_9.2_beta_4__iPad_2_WiFi__13C75.zip","icon":"fas fa-download","type":"ipsw","size":1393551020},{"text":"iPad 2 Wi-Fi (Mid 2012)","key":"iPad2,4","link":"http://adcdownload.apple.com/iOS/iOS_9.2_beta_4/iOS_9.2_beta_4__iPad_2_WiFi_Rev_A__13C75.zip","icon":"fas fa-download","type":"ipsw","size":1394260794}],"img":"iPad2,4","imgFlags":{"internal":true,"dark":false},"icons":[],"link":"/device/iPad-2"}]}]}