{"title":{"header":"iOS 18.5 RC Simulator (22F77)","subtitle":{"text":"May 15, 2025 — <code style=\"background: none; padding-inline: 2px; font-size: 1em;\">22F77</code>","tags":[{"text":"RC","colour":"#ab47bc"}]},"image":{"url":null,"align":"right","images":[]}},"sections":[{"type":"buttons","class":"wrap","content":[{"text":"aar (8.9 GB)","key":"iOS Simulator","link":"https://updates.cdn-apple.com/2025/mobileassets/043-39934/7E9105AB-C0A9-4842-9F83-51647042E3BF/com_apple_MobileAsset_iOSSimulatorRuntime/1DDBFF7D-AF07-4905-B63C-25AE53C4702A.aar","decryptionKey":"15wwfkrSon24ww9+9QlQlGA2R0LtJhwI7kTTmiYCUNk=","icon":"fas fa-fw fa-download","type":"aar","size":8858370048,"active":true}]},{"title":"Devices","type":"grid","class":"smallTitle","content":[{"title":"iOS Simulator","key":"iOS Simulator","subtitle":"Oct 2, 2011","subgroups":[],"links":[],"img":"iOS Simulator","imgFlags":{"internal":true,"images":[{"id":0,"dark":false}]},"icons":[],"link":"/device/identifier/iOS-Simulator","singleDownload":{"text":"aar (8.9 GB)","key":"iOS Simulator","link":"https://updates.cdn-apple.com/2025/mobileassets/043-39934/7E9105AB-C0A9-4842-9F83-51647042E3BF/com_apple_MobileAsset_iOSSimulatorRuntime/1DDBFF7D-AF07-4905-B63C-25AE53C4702A.aar","decryptionKey":"15wwfkrSon24ww9+9QlQlGA2R0LtJhwI7kTTmiYCUNk=","icon":"fas fa-fw fa-download","type":"aar","size":8858370048,"active":true}}]}]}