{"title":{"header":"iOS 14.5 beta 4","subtitle":{"text":"Mar 15, 2021 — <code style=\"background: none; padding-inline: 2px; font-size: 1em;\">18E5178a</code>","tags":[{"text":"Beta","colour":"#ab47bc"}]},"image":{"url":"ios14","align":"left"}},"sections":[{"title":"Devices","type":"grid","class":"smallTitle","content":[{"title":"iPod touch (7th generation)","key":"iPod9,1","subtitle":"May 28, 2019","subgroups":[],"links":[{"text":"IPSW","key":"iPod9,1","link":"https://updates.cdn-apple.com/2021WinterSeed/fullrestores/071-17235/04EAC610-C273-4B8E-B981-7A5816DA9FD7/iPodtouch_7_14.5_18E5178a_Restore.ipsw","icon":"fas fa-download","type":"ipsw","size":4477447452}],"img":"iPod9,1","imgFlags":{"internal":true,"dark":false},"icons":[],"link":"/device/identifier/iPod9,1"},{"title":"iPhone 12 Pro","key":"iPhone-12-Pro-series","subtitle":"Oct 23, 2020","subgroups":[{"name":"iPhone 12 Pro","type":"iPhone","order":0,"devices":["iPhone13,3"]},{"name":"iPhone 12 Pro Max","type":"iPhone","order":1,"devices":["iPhone13,4"]}],"links":[{"text":"iPhone 12 Pro","key":"iPhone13,3","link":"https://updates.cdn-apple.com/2021WinterSeed/fullrestores/071-17324/16B7C45A-09DB-49C3-9AB7-0BAA70C8AFCF/iPhone13,2,iPhone13,3_14.5_18E5178a_Restore.ipsw","icon":"fas fa-download","type":"ipsw","size":5810941273},{"text":"iPhone 12 Pro Max","key":"iPhone13,4","link":"https://updates.cdn-apple.com/2021WinterSeed/fullrestores/071-17279/CD72B2AE-8207-487A-A56D-8AA5EF91D85D/iPhone13,4_14.5_18E5178a_Restore.ipsw","icon":"fas fa-download","type":"ipsw","size":5689809080}],"img":"iPhone13,4","imgFlags":{"internal":true,"dark":true},"icons":[],"link":"/device/iPhone-12-Pro-series"},{"title":"iPhone SE (2nd generation)","key":"iPhone12,8","subtitle":"Apr 24, 2020","subgroups":[],"links":[{"text":"IPSW","key":"iPhone12,8","link":"https://updates.cdn-apple.com/2021WinterSeed/fullrestores/071-17236/8C298805-5F60-4520-B07B-2E299BF972E8/iPhone12,8_14.5_18E5178a_Restore.ipsw","icon":"fas fa-download","type":"ipsw","size":5248691858}],"img":"iPhone12,8","imgFlags":{"internal":true,"dark":true},"icons":[],"link":"/device/identifier/iPhone12,8"},{"title":"iPhone 11","key":"iPhone12,1","subtitle":"Sep 20, 2019","subgroups":[],"links":[{"text":"IPSW","key":"iPhone12,1","link":"https://updates.cdn-apple.com/2021WinterSeed/fullrestores/071-17108/7CB6719A-3B66-472D-9073-80DD857C4358/iPhone11,8,iPhone12,1_14.5_18E5178a_Restore.ipsw","icon":"fas fa-download","type":"ipsw","size":5864440468}],"img":"iPhone12,1","imgFlags":{"internal":true,"dark":true},"icons":[],"link":"/device/identifier/iPhone12,1"},{"title":"iPhone XR","key":"iPhone11,8","subtitle":"Oct 26, 2018","subgroups":[],"links":[{"text":"IPSW","key":"iPhone11,8","link":"https://updates.cdn-apple.com/2021WinterSeed/fullrestores/071-17108/7CB6719A-3B66-472D-9073-80DD857C4358/iPhone11,8,iPhone12,1_14.5_18E5178a_Restore.ipsw","icon":"fas fa-download","type":"ipsw","size":5864440468}],"img":"iPhone11,8","imgFlags":{"internal":true,"dark":false},"icons":[],"link":"/device/identifier/iPhone11,8"},{"title":"iPhone 12","key":"iPhone-12-series","subtitle":"Nov 13, 2020","subgroups":[{"name":"iPhone 12","type":"iPhone","order":0,"devices":["iPhone13,2"]},{"name":"iPhone 12 mini","type":"iPhone","order":1,"devices":["iPhone13,1"]}],"links":[{"text":"iPhone 12 mini","key":"iPhone13,1","link":"https://updates.cdn-apple.com/2021WinterSeed/fullrestores/071-17285/CD2851F3-4A9C-463E-8986-D61A5A1E8F19/iPhone13,1_14.5_18E5178a_Restore.ipsw","icon":"fas fa-download","type":"ipsw","size":5612563982},{"text":"iPhone 12","key":"iPhone13,2","link":"https://updates.cdn-apple.com/2021WinterSeed/fullrestores/071-17324/16B7C45A-09DB-49C3-9AB7-0BAA70C8AFCF/iPhone13,2,iPhone13,3_14.5_18E5178a_Restore.ipsw","icon":"fas fa-download","type":"ipsw","size":5810941273}],"img":"iPhone13,2","imgFlags":{"internal":true,"dark":true},"icons":[],"link":"/device/iPhone-12-series"},{"title":"iPhone 11 Pro","key":"iPhone-11-Pro-series","subtitle":"Sep 20, 2019","subgroups":[{"name":"iPhone 11 Pro","type":"iPhone","order":0,"devices":["iPhone12,3"]},{"name":"iPhone 11 Pro Max","type":"iPhone","order":1,"devices":["iPhone12,5"]}],"links":[{"text":"IPSW","key":"iPhone12,5","link":"https://updates.cdn-apple.com/2021WinterSeed/fullrestores/071-17171/166B9224-4DC2-44CE-9A5B-61AF08534180/iPhone11,2,iPhone11,4,iPhone11,6,iPhone12,3,iPhone12,5_14.5_18E5178a_Restore.ipsw","icon":"fas fa-download","type":"ipsw","size":6460601930}],"img":"iPhone12,5","imgFlags":{"internal":true,"dark":true},"icons":[],"link":"/device/iPhone-11-Pro-series"},{"title":"iPhone XS","key":"iPhone-XS-series","subtitle":"Sep 21, 2018","subgroups":[{"name":"iPhone XS","type":"iPhone","order":0,"devices":["iPhone11,2"]},{"name":"iPhone XS Max","type":"iPhone","order":1,"devices":["iPhone11,4","iPhone11,6"]}],"links":[{"text":"IPSW","key":"iPhone11,4","link":"https://updates.cdn-apple.com/2021WinterSeed/fullrestores/071-17171/166B9224-4DC2-44CE-9A5B-61AF08534180/iPhone11,2,iPhone11,4,iPhone11,6,iPhone12,3,iPhone12,5_14.5_18E5178a_Restore.ipsw","icon":"fas fa-download","type":"ipsw","size":6460601930}],"img":"iPhone11,6","imgFlags":{"internal":true,"dark":false},"icons":[],"link":"/device/iPhone-XS-series"},{"title":"iPhone X","key":"iPhone-X","subtitle":"Nov 3, 2017","subgroups":[],"links":[{"text":"IPSW","key":"iPhone10,6","link":"https://updates.cdn-apple.com/2021WinterSeed/fullrestores/071-17001/7F827FA8-BB3C-48CE-B970-C5785A3BADF8/iPhone10,3,iPhone10,6_14.5_18E5178a_Restore.ipsw","icon":"fas fa-download","type":"ipsw","size":5195449091}],"img":"iPhone10,6","imgFlags":{"internal":true,"dark":false},"icons":[],"link":"/device/iPhone-X"},{"title":"iPhone 8","key":"iPhone-8-series","subtitle":"Sep 22, 2017","subgroups":[{"name":"iPhone 8","type":"iPhone","order":0,"devices":["iPhone10,1","iPhone10,4"]},{"name":"iPhone 8 Plus","type":"iPhone","order":1,"devices":["iPhone10,2","iPhone10,5"]}],"links":[{"text":"iPhone 8","key":"iPhone10,4","link":"https://updates.cdn-apple.com/2021WinterSeed/fullrestores/071-16891/830DC734-14AA-49FB-997E-E2851C0CC10A/iPhone_4.7_P3_14.5_18E5178a_Restore.ipsw","icon":"fas fa-download","type":"ipsw","size":5038998643},{"text":"iPhone 8 Plus","key":"iPhone10,5","link":"https://updates.cdn-apple.com/2021WinterSeed/fullrestores/071-17117/D88324E9-238A-4F85-97DB-AE8326377DD6/iPhone_5.5_P3_14.5_18E5178a_Restore.ipsw","icon":"fas fa-download","type":"ipsw","size":5255341980}],"img":"iPhone10,5","imgFlags":{"internal":true,"dark":false},"icons":[],"link":"/device/iPhone-8-series"},{"title":"iPhone 7","key":"iPhone-7-series","subtitle":"Sep 16, 2016","subgroups":[{"name":"iPhone 7","type":"iPhone","order":0,"devices":["iPhone9,1","iPhone9,3"]},{"name":"iPhone 7 Plus","type":"iPhone","order":1,"devices":["iPhone9,2","iPhone9,4"]}],"links":[{"text":"iPhone 7","key":"iPhone9,3","link":"https://updates.cdn-apple.com/2021WinterSeed/fullrestores/071-16891/830DC734-14AA-49FB-997E-E2851C0CC10A/iPhone_4.7_P3_14.5_18E5178a_Restore.ipsw","icon":"fas fa-download","type":"ipsw","size":5038998643},{"text":"iPhone 7 Plus","key":"iPhone9,4","link":"https://updates.cdn-apple.com/2021WinterSeed/fullrestores/071-17117/D88324E9-238A-4F85-97DB-AE8326377DD6/iPhone_5.5_P3_14.5_18E5178a_Restore.ipsw","icon":"fas fa-download","type":"ipsw","size":5255341980}],"img":"iPhone9,4","imgFlags":{"internal":true,"dark":false},"icons":[],"link":"/device/iPhone-7-series"},{"title":"iPhone SE (1st generation)","key":"iPhone8,4","subtitle":"Mar 31, 2016","subgroups":[],"links":[{"text":"IPSW","key":"iPhone8,4","link":"https://updates.cdn-apple.com/2021WinterSeed/fullrestores/071-17140/4B219B0E-2409-4FE5-8DB3-85EC91F4FAB3/iPhone_4.0_64bit_14.5_18E5178a_Restore.ipsw","icon":"fas fa-download","type":"ipsw","size":4653615034}],"img":"iPhone8,4","imgFlags":{"internal":true,"dark":false},"icons":[],"link":"/device/identifier/iPhone8,4"},{"title":"iPhone 6s","key":"iPhone-6s-series","subtitle":"Sep 25, 2015","subgroups":[{"name":"iPhone 6s","type":"iPhone","order":0,"devices":["iPhone8,1"]},{"name":"iPhone 6s Plus","type":"iPhone","order":1,"devices":["iPhone8,2"]}],"links":[{"text":"iPhone 6s Plus","key":"iPhone8,2","link":"https://updates.cdn-apple.com/2021WinterSeed/fullrestores/071-16869/709BA127-34CD-4E88-BB85-9AA365217DDD/iPhone_5.5_14.5_18E5178a_Restore.ipsw","icon":"fas fa-download","type":"ipsw","size":4897788191},{"text":"iPhone 6s","key":"iPhone8,1","link":"https://updates.cdn-apple.com/2021WinterSeed/fullrestores/071-16954/8C9B411B-9078-4BC1-BF97-3430407F18D7/iPhone_4.7_14.5_18E5178a_Restore.ipsw","icon":"fas fa-download","type":"ipsw","size":4685199989}],"img":"iPhone8,2","imgFlags":{"internal":true,"dark":false},"icons":[],"link":"/device/iPhone-6s-series"}]},{"title":"Jailbreaks","type":"list","class":"smallTitle noListDisc customListDisc","content":[{"text":"checkra1n","link":"/jailbreak/checkra1n","children":[{"text":"iPhone 6s","link":"/device/identifier/iPhone8,1"},{"text":"iPhone 6s Plus","link":"/device/identifier/iPhone8,2"},{"text":"iPhone SE (1st generation)","link":"/device/identifier/iPhone8,4"},{"text":"iPhone 7 (CDMA)","link":"/device/identifier/iPhone9,1"},{"text":"iPhone 7 Plus (CDMA)","link":"/device/identifier/iPhone9,2"},{"text":"iPhone 7 (GSM)","link":"/device/identifier/iPhone9,3"},{"text":"iPhone 7 Plus (GSM)","link":"/device/identifier/iPhone9,4"},{"text":"iPhone 8 (CDMA)","link":"/device/identifier/iPhone10,1"},{"text":"iPhone 8 Plus (CDMA)","link":"/device/identifier/iPhone10,2"},{"text":"iPhone X (CDMA)","link":"/device/identifier/iPhone10,3"},{"text":"iPhone 8 (GSM)","link":"/device/identifier/iPhone10,4"},{"text":"iPhone 8 Plus (GSM)","link":"/device/identifier/iPhone10,5"},{"text":"iPhone X (GSM)","link":"/device/identifier/iPhone10,6"},{"text":"iPod touch (7th generation)","link":"/device/identifier/iPod9,1"}],"showLess":"Hide devices","showMore":"Show devices"},{"text":"Taurine","link":"/jailbreak/Taurine","hoverLink":{"text":"Supports all devices","icon":"check","hideWhenInactive":false}}]}]}