{"title":{"header":"iOS 9.3 beta 7","subtitle":{"text":"Mar 14, 2016 — <code style=\"background: none; padding-inline: 2px; font-size: 1em;\">13E5234a</code>","tags":[{"text":"Beta","colour":"#ab47bc"}]},"image":{"url":"ios9","align":"left"}},"sections":[{"title":"Devices","type":"grid","class":"smallTitle","content":[{"title":"iPhone 6s","key":"iPhone-6s-series","subtitle":"Sep 25, 2015","subgroups":[{"name":"iPhone 6s","type":"iPhone","order":0,"devices":["iPhone8,1"]},{"name":"iPhone 6s Plus","type":"iPhone","order":1,"devices":["iPhone8,2"]}],"links":[{"text":"iPhone 6s Plus","key":"iPhone8,2","link":"http://appldnld.apple.com/ios9.3seed/058-41736-20160315-81504E1E-E97D-11E5-B96A-F367BD379832/iPhone8,2_9.3_13E5234a_Restore.ipsw","icon":"fas fa-download","type":"ipsw","size":2435045567},{"text":"iPhone 6s","key":"iPhone8,1","link":"http://appldnld.apple.com/ios9.3seed/031-53038-20160315-814FEA8C-E97D-11E5-AA6B-F267BD379832/iPhone8,1_9.3_13E5234a_Restore.ipsw","icon":"fas fa-download","type":"ipsw","size":2198109877}],"img":"iPhone8,2","imgFlags":{"internal":true,"dark":false},"icons":[],"link":"/device/iPhone-6s-series"}]}]}