{"title":{"header":"iOS 18.3 beta 3","subtitle":{"text":"Jan 16, 2025 — <code style=\"background: none; padding-inline: 2px; font-size: 1em;\">22D5055b</code>","tags":[{"text":"Beta","colour":"#ab47bc"}]},"image":{"url":"ios18","align":"left"}},"sections":[{"title":"Devices","type":"grid","class":"smallTitle","content":[{"title":"iPhone 16 Pro","key":"iPhone-16-Pro-series","subtitle":"Sep 20, 2024","subgroups":[{"name":"iPhone 16 Pro","type":"iPhone","devices":["iPhone17,1"]},{"name":"iPhone 16 Pro Max","type":"iPhone","devices":["iPhone17,2"]}],"links":[{"text":"iPhone 16 Pro Max","key":"iPhone17,2","link":"https://updates.cdn-apple.com/2025WinterSeed/fullrestores/072-61797/B0862619-C342-4BE1-972D-DFFBE0647AC6/iPhone17,2_18.3_22D5055b_Restore.ipsw","icon":"fas fa-download","type":"ipsw","size":9468879218},{"text":"iPhone 16 Pro","key":"iPhone17,1","link":"https://updates.cdn-apple.com/2025WinterSeed/fullrestores/072-61840/671251EE-1906-4397-BBEA-E051DDF8806B/iPhone17,1_18.3_22D5055b_Restore.ipsw","icon":"fas fa-download","type":"ipsw","size":9469419129}],"img":"iPhone17,1","imgFlags":{"internal":true,"dark":false},"icons":[],"link":"/device/iPhone-16-Pro-series"},{"title":"iPhone 16","key":"iPhone-16-series","subtitle":"Sep 20, 2024","subgroups":[{"name":"iPhone 16","type":"iPhone","devices":["iPhone17,3"]},{"name":"iPhone 16 Plus","type":"iPhone","devices":["iPhone17,4"]}],"links":[{"text":"iPhone 16 Plus","key":"iPhone17,4","link":"https://updates.cdn-apple.com/2025WinterSeed/fullrestores/072-61831/1D9070FE-9362-4D20-963D-3DF13DDBB34F/iPhone17,4_18.3_22D5055b_Restore.ipsw","icon":"fas fa-download","type":"ipsw","size":9396738773},{"text":"iPhone 16","key":"iPhone17,3","link":"https://updates.cdn-apple.com/2025WinterSeed/fullrestores/072-61776/65C1C679-51A8-4061-A0FF-6BD898ADF793/iPhone17,3_18.3_22D5055b_Restore.ipsw","icon":"fas fa-download","type":"ipsw","size":9422831817}],"img":"iPhone17,3","imgFlags":{"internal":true,"dark":false},"icons":[],"link":"/device/iPhone-16-series"},{"title":"iPhone 15 Pro","key":"iPhone-15-Pro-series","subtitle":"Sep 22, 2023","subgroups":[{"name":"iPhone 15 Pro","type":"iPhone","devices":["iPhone16,1"]},{"name":"iPhone 15 Pro Max","type":"iPhone","devices":["iPhone16,2"]}],"links":[{"text":"iPhone 15 Pro Max","key":"iPhone16,2","link":"https://updates.cdn-apple.com/2025WinterSeed/fullrestores/072-61800/0D5DAF16-263B-4515-BFDA-9276775849D4/iPhone16,2_18.3_22D5055b_Restore.ipsw","icon":"fas fa-download","type":"ipsw","size":9190881116},{"text":"iPhone 15 Pro","key":"iPhone16,1","link":"https://updates.cdn-apple.com/2025WinterSeed/fullrestores/072-61762/78A11FA6-A66C-4A1D-8565-6973775BF0F3/iPhone16,1_18.3_22D5055b_Restore.ipsw","icon":"fas fa-download","type":"ipsw","size":9190751300}],"img":"iPhone16,2","imgFlags":{"internal":true,"dark":false},"icons":[],"link":"/device/iPhone-15-Pro-series"},{"title":"iPhone 15","key":"iPhone-15-series","subtitle":"Sep 22, 2023","subgroups":[{"name":"iPhone 15","type":"iPhone","devices":["iPhone15,4"]},{"name":"iPhone 15 Plus","type":"iPhone","devices":["iPhone15,5"]}],"links":[{"text":"iPhone 15 Plus","key":"iPhone15,5","link":"https://updates.cdn-apple.com/2025WinterSeed/fullrestores/072-61555/3ED01C2F-364A-4996-A28C-AE1C5AC65814/iPhone15,5_18.3_22D5055b_Restore.ipsw","icon":"fas fa-download","type":"ipsw","size":8919531252},{"text":"iPhone 15","key":"iPhone15,4","link":"https://updates.cdn-apple.com/2025WinterSeed/fullrestores/072-61615/29662D40-F67C-4A25-85A0-0FAECF436F0C/iPhone15,4_18.3_22D5055b_Restore.ipsw","icon":"fas fa-download","type":"ipsw","size":8919480478}],"img":"iPhone15,5","imgFlags":{"internal":true,"dark":false},"icons":[],"link":"/device/iPhone-15-series"},{"title":"iPhone 14 Pro","key":"iPhone-14-Pro-series","subtitle":"Sep 16, 2022","subgroups":[{"name":"iPhone 14 Pro","type":"iPhone","devices":["iPhone15,2"]},{"name":"iPhone 14 Pro Max","type":"iPhone","devices":["iPhone15,3"]}],"links":[{"text":"iPhone 14 Pro Max","key":"iPhone15,3","link":"https://updates.cdn-apple.com/2025WinterSeed/fullrestores/072-61744/A263EC20-7E1A-4180-BF79-3C06AA693989/iPhone15,3_18.3_22D5055b_Restore.ipsw","icon":"fas fa-download","type":"ipsw","size":8906961149},{"text":"iPhone 14 Pro","key":"iPhone15,2","link":"https://updates.cdn-apple.com/2025WinterSeed/fullrestores/072-61895/654DBBD6-E67A-4443-BC54-4A7AC9CC977C/iPhone15,2_18.3_22D5055b_Restore.ipsw","icon":"fas fa-download","type":"ipsw","size":8930183024}],"img":"iPhone15,3","imgFlags":{"internal":true,"dark":false},"icons":[],"link":"/device/iPhone-14-Pro-series"},{"title":"iPhone SE (3rd generation)","key":"iPhone14,6","subtitle":"Mar 18, 2022","subgroups":[],"links":[{"text":"IPSW","key":"iPhone14,6","link":"https://updates.cdn-apple.com/2025WinterSeed/fullrestores/072-61474/2D7FB320-0DF0-44FE-BDEB-8582A6E44C65/iPhone14,6_18.3_22D5055b_Restore.ipsw","icon":"fas fa-download","type":"ipsw","size":8508733171}],"img":"iPhone14,6","imgFlags":{"internal":true,"dark":true},"icons":[],"link":"/device/identifier/iPhone14,6"},{"title":"iPhone SE (2nd generation)","key":"iPhone12,8","subtitle":"Apr 24, 2020","subgroups":[],"links":[{"text":"IPSW","key":"iPhone12,8","link":"https://updates.cdn-apple.com/2025WinterSeed/fullrestores/072-61477/6BDC4C80-E374-4576-85CF-7C01F5B458EF/iPhone12,8_18.3_22D5055b_Restore.ipsw","icon":"fas fa-download","type":"ipsw","size":8147282099}],"img":"iPhone12,8","imgFlags":{"internal":true,"dark":true},"icons":[],"link":"/device/identifier/iPhone12,8"},{"title":"iPhone XR","key":"iPhone11,8","subtitle":"Oct 26, 2018","subgroups":[],"links":[{"text":"IPSW","key":"iPhone11,8","link":"https://updates.cdn-apple.com/2025WinterSeed/fullrestores/072-61604/35C037BD-FF48-4395-8516-C4DF14F88893/iPhone11,8_18.3_22D5055b_Restore.ipsw","icon":"fas fa-download","type":"ipsw","size":8344917761}],"img":"iPhone11,8","imgFlags":{"internal":true,"dark":false},"icons":[],"link":"/device/identifier/iPhone11,8"},{"title":"iPhone 14","key":"iPhone-14-series","subtitle":"Oct 7, 2022","subgroups":[{"name":"iPhone 14","type":"iPhone","devices":["iPhone14,7"]},{"name":"iPhone 14 Plus","type":"iPhone","devices":["iPhone14,8"]}],"links":[{"text":"iPhone 14 Plus","key":"iPhone14,8","link":"https://updates.cdn-apple.com/2025WinterSeed/fullrestores/072-61495/43675019-B49F-48AC-9DF3-82C5A050B3EF/iPhone14,8_18.3_22D5055b_Restore.ipsw","icon":"fas fa-download","type":"ipsw","size":8770948743},{"text":"iPhone 14","key":"iPhone14,7","link":"https://updates.cdn-apple.com/2025WinterSeed/fullrestores/072-61679/7A64FF98-48F8-499F-9DD2-4D8116D797F4/iPhone14,7_18.3_22D5055b_Restore.ipsw","icon":"fas fa-download","type":"ipsw","size":8771849704}],"img":"iPhone14,8","imgFlags":{"internal":true,"dark":false},"icons":[],"link":"/device/iPhone-14-series"},{"title":"iPhone 13 Pro","key":"iPhone-13-Pro-series","subtitle":"Sep 24, 2021","subgroups":[{"name":"iPhone 13 Pro","type":"iPhone","order":0,"devices":["iPhone14,2"]},{"name":"iPhone 13 Pro Max","type":"iPhone","order":1,"devices":["iPhone14,3"]}],"links":[{"text":"iPhone 13 Pro Max","key":"iPhone14,3","link":"https://updates.cdn-apple.com/2025WinterSeed/fullrestores/072-61533/5710E53D-E590-49F7-9E54-4376C43DE5AA/iPhone14,3_18.3_22D5055b_Restore.ipsw","icon":"fas fa-download","type":"ipsw","size":8817845096},{"text":"iPhone 13 Pro","key":"iPhone14,2","link":"https://updates.cdn-apple.com/2025WinterSeed/fullrestores/072-61603/E3D2D0DC-DC07-4AC8-BF7B-9C3ED88E923F/iPhone14,2_18.3_22D5055b_Restore.ipsw","icon":"fas fa-download","type":"ipsw","size":8817844098}],"img":"iPhone14,3","imgFlags":{"internal":true,"dark":true},"icons":[],"link":"/device/iPhone-13-Pro-series"},{"title":"iPhone 13","key":"iPhone-13-series","subtitle":"Sep 24, 2021","subgroups":[{"name":"iPhone 13","type":"iPhone","order":0,"devices":["iPhone14,5"]},{"name":"iPhone 13 mini","type":"iPhone","order":1,"devices":["iPhone14,4"]}],"links":[{"text":"iPhone 13 mini","key":"iPhone14,4","link":"https://updates.cdn-apple.com/2025WinterSeed/fullrestores/072-61513/92A247CB-0EDA-425A-AD12-387C57CEDFA5/iPhone14,4_18.3_22D5055b_Restore.ipsw","icon":"fas fa-download","type":"ipsw","size":8773033932},{"text":"iPhone 13","key":"iPhone14,5","link":"https://updates.cdn-apple.com/2025WinterSeed/fullrestores/072-61899/81F2809E-FBE3-4BE5-AAFF-1E1792E96030/iPhone14,5_18.3_22D5055b_Restore.ipsw","icon":"fas fa-download","type":"ipsw","size":8751243731}],"img":"iPhone14,5","imgFlags":{"internal":true,"dark":true},"icons":[],"link":"/device/iPhone-13-series"},{"title":"iPhone 12 Pro","key":"iPhone-12-Pro-series","subtitle":"Oct 23, 2020","subgroups":[{"name":"iPhone 12 Pro","type":"iPhone","order":0,"devices":["iPhone13,3"]},{"name":"iPhone 12 Pro Max","type":"iPhone","order":1,"devices":["iPhone13,4"]}],"links":[{"text":"iPhone 12 Pro","key":"iPhone13,3","link":"https://updates.cdn-apple.com/2025WinterSeed/fullrestores/072-61643/9E401BE0-4F8D-46C0-925A-E4F5BE5C50DA/iPhone13,2,iPhone13,3_18.3_22D5055b_Restore.ipsw","icon":"fas fa-download","type":"ipsw","size":8836677834},{"text":"iPhone 12 Pro Max","key":"iPhone13,4","link":"https://updates.cdn-apple.com/2025WinterSeed/fullrestores/072-61649/9AEB502C-F0E3-4A4B-A0BF-5456B01C8E41/iPhone13,4_18.3_22D5055b_Restore.ipsw","icon":"fas fa-download","type":"ipsw","size":8801016700}],"img":"iPhone13,4","imgFlags":{"internal":true,"dark":true},"icons":[],"link":"/device/iPhone-12-Pro-series"},{"title":"iPhone 12","key":"iPhone-12-series","subtitle":"Nov 13, 2020","subgroups":[{"name":"iPhone 12","type":"iPhone","order":0,"devices":["iPhone13,2"]},{"name":"iPhone 12 mini","type":"iPhone","order":1,"devices":["iPhone13,1"]}],"links":[{"text":"iPhone 12 mini","key":"iPhone13,1","link":"https://updates.cdn-apple.com/2025WinterSeed/fullrestores/072-61791/E6F4650B-A96E-425A-9FE7-1B22FF8E81BB/iPhone13,1_18.3_22D5055b_Restore.ipsw","icon":"fas fa-download","type":"ipsw","size":8666435173},{"text":"iPhone 12","key":"iPhone13,2","link":"https://updates.cdn-apple.com/2025WinterSeed/fullrestores/072-61643/9E401BE0-4F8D-46C0-925A-E4F5BE5C50DA/iPhone13,2,iPhone13,3_18.3_22D5055b_Restore.ipsw","icon":"fas fa-download","type":"ipsw","size":8836677834}],"img":"iPhone13,2","imgFlags":{"internal":true,"dark":true},"icons":[],"link":"/device/iPhone-12-series"},{"title":"iPhone 11 Pro","key":"iPhone-11-Pro-series","subtitle":"Sep 20, 2019","subgroups":[{"name":"iPhone 11 Pro","type":"iPhone","order":0,"devices":["iPhone12,3"]},{"name":"iPhone 11 Pro Max","type":"iPhone","order":1,"devices":["iPhone12,5"]}],"links":[{"text":"IPSW","key":"iPhone12,5","link":"https://updates.cdn-apple.com/2025WinterSeed/fullrestores/072-61844/884869DE-BE22-4F3E-9E9F-B3E3C1BC798A/iPhone12,3,iPhone12,5_18.3_22D5055b_Restore.ipsw","icon":"fas fa-download","type":"ipsw","size":8367670226}],"img":"iPhone12,5","imgFlags":{"internal":true,"dark":true},"icons":[],"link":"/device/iPhone-11-Pro-series"},{"title":"iPhone 11","key":"iPhone12,1","subtitle":"Sep 20, 2019","subgroups":[],"links":[{"text":"IPSW","key":"iPhone12,1","link":"https://updates.cdn-apple.com/2025WinterSeed/fullrestores/072-61591/1744FED7-D2FE-4E71-9E59-1D59DD9E64FA/iPhone12,1_18.3_22D5055b_Restore.ipsw","icon":"fas fa-download","type":"ipsw","size":8175171013}],"img":"iPhone12,1","imgFlags":{"internal":true,"dark":true},"icons":[],"link":"/device/identifier/iPhone12,1"},{"title":"iPhone XS","key":"iPhone-XS-series","subtitle":"Sep 21, 2018","subgroups":[{"name":"iPhone XS","type":"iPhone","order":0,"devices":["iPhone11,2"]},{"name":"iPhone XS Max","type":"iPhone","order":1,"devices":["iPhone11,4","iPhone11,6"]}],"links":[{"text":"IPSW","key":"iPhone11,4","link":"https://updates.cdn-apple.com/2025WinterSeed/fullrestores/072-61811/FE510550-894D-4DB7-96A2-52403D7CD513/iPhone11,2,iPhone11,4,iPhone11,6_18.3_22D5055b_Restore.ipsw","icon":"fas fa-download","type":"ipsw","size":8509722561}],"img":"iPhone11,6","imgFlags":{"internal":true,"dark":false},"icons":[],"link":"/device/iPhone-XS-series"}]},{"title":"Jailbreaks","type":"list","class":"smallTitle noListDisc customListDisc","content":[{"text":"palera1n","link":"/jailbreak/palera1n","children":[],"showLess":"Hide devices","showMore":"Show devices"}]}]}