{"title":{"header":"OS X 10.8.2","subtitle":{"text":"<code style=\"background: none; padding-inline: 2px; font-size: 1em;\">12C2017</code>","tags":[{"text":"Internal","colour":"#f0ad05"}]},"image":{"url":"Mountain Lion","align":"left"}},"sections":[{"title":"Devices","type":"grid","class":"smallTitle","content":[{"title":"iMac (27-inch, Late 2012)","key":"iMac13,2","subtitle":"Oct 23, 2012","subgroups":[],"links":[],"img":"iMac13,2","imgFlags":{"internal":true,"dark":false},"icons":[],"link":"/device/identifier/iMac13,2"},{"title":"iMac (21.5-inch, Late 2012)","key":"iMac13,1","subtitle":"Oct 23, 2012","subgroups":[],"links":[],"img":"iMac13,1","imgFlags":{"internal":true,"dark":false},"icons":[],"link":"/device/identifier/iMac13,1"},{"title":"MacBook Pro (Retina, 13-inch, Late 2012)","key":"MacBookPro10,2-Late-2012","subtitle":"Oct 23, 2012","subgroups":[],"links":[],"img":"MacBookPro10,2-Late-2012","imgFlags":{"internal":true,"dark":false},"icons":[],"link":"/device/identifier/MacBookPro10,2-Late-2012"}]}]}