{"title":{"header":"Rosetta 15.2 beta 4","subtitle":{"text":"Nov 20, 2024 — <code style=\"background: none; padding-inline: 2px; font-size: 1em;\">24C5089c</code>","tags":[{"text":"Beta","colour":"#ab47bc"}]},"image":{"url":null,"align":"right"}},"sections":[{"type":"buttons","class":"wrap","content":[{"text":"pkg (446.2 KB)","key":"Rosetta","link":"https://swcdn.apple.com/content/downloads/32/37/072-35575-A_ZTP4GLOVGP/mbpavezflxxecyzkza9ck1p1q2ydgfq47z/RosettaUpdateAuto.pkg","icon":"fas fa-download","type":"pkg","size":446215}]},{"title":"Devices","type":"grid","class":"smallTitle","content":[{"title":"Rosetta","key":"Rosetta","subtitle":"Sep 17, 2020","subgroups":[],"links":[],"img":"Rosetta","imgFlags":{"internal":true,"dark":false},"icons":[],"link":"/device/identifier/Rosetta","singleDownload":{"text":"pkg (446.2 KB)","key":"Rosetta","link":"https://swcdn.apple.com/content/downloads/32/37/072-35575-A_ZTP4GLOVGP/mbpavezflxxecyzkza9ck1p1q2ydgfq47z/RosettaUpdateAuto.pkg","icon":"fas fa-download","type":"pkg","size":446215}}]}]}