{"title":{"header":"Rosetta 11.6.2","subtitle":{"text":"Dec 13, 2021 — <code style=\"background: none; padding-inline: 2px; font-size: 1em;\">20G314</code>","tags":[{"text":"Release","colour":"#039be5"}]},"image":{"url":null,"align":"right"}},"sections":[{"type":"buttons","class":"wrap","content":[{"text":"pkg (200.7 KB)","key":"Rosetta","link":"https://swcdn.apple.com/content/downloads/21/61/002-42344-A_C1GC1MLDSW/gwwrrxbn72uyuohgb7v7hjwpypdih4yw4m/RosettaUpdateAuto.pkg","icon":"fas fa-download","type":"pkg","size":200734}]},{"title":"Devices","type":"grid","class":"smallTitle","content":[{"title":"Rosetta","key":"Rosetta","subtitle":"Sep 17, 2020","subgroups":[],"links":[],"img":"Rosetta","imgFlags":{"internal":true,"dark":false},"icons":[],"link":"/device/identifier/Rosetta","singleDownload":{"text":"pkg (200.7 KB)","key":"Rosetta","link":"https://swcdn.apple.com/content/downloads/21/61/002-42344-A_C1GC1MLDSW/gwwrrxbn72uyuohgb7v7hjwpypdih4yw4m/RosettaUpdateAuto.pkg","icon":"fas fa-download","type":"pkg","size":200734}}]}]}