{"title":{"header":"Rosetta 14.8.5 RC 4 (23J423)","subtitle":{"text":"Mar 18, 2026 — <code style=\"background: none; padding-inline: 2px; font-size: 1em;\">23J423</code>","tags":[{"text":"RC","colour":"#ab47bc"}]},"image":{"url":null,"align":"right","images":[]}},"sections":[{"type":"buttons","class":"wrap","content":[{"text":"pkg (384.1 KB)","key":"Rosetta","link":"https://swcdn.apple.com/content/downloads/15/52/047-96014-A_UZ78IF9DJK/z4z5nilehftd9r9cfmy54thxf6250rclbn/RosettaUpdateAuto.pkg","icon":"fas fa-fw fa-download","type":"pkg","size":384137,"active":true}]},{"title":"Devices","type":"grid","class":"smallTitle","content":[{"title":"Rosetta","key":"Rosetta","subtitle":"Sep 17, 2020","subgroups":[],"links":[],"img":"Rosetta","imgFlags":{"internal":true,"images":[{"id":0,"dark":false}]},"icons":[],"link":"/device/identifier/Rosetta","singleDownload":{"text":"pkg (384.1 KB)","key":"Rosetta","link":"https://swcdn.apple.com/content/downloads/15/52/047-96014-A_UZ78IF9DJK/z4z5nilehftd9r9cfmy54thxf6250rclbn/RosettaUpdateAuto.pkg","icon":"fas fa-fw fa-download","type":"pkg","size":384137,"active":true}}]}]}