{"title":{"header":"Safari 9.1","subtitle":{"text":"Mar 21, 2016","tags":[{"text":"Release","colour":"#039be5"}]},"image":{"url":null,"align":"right"}},"sections":[{"type":"buttons","class":"wrap","content":[{"text":"pkg (NaN undefined)","key":"Safari (macOS)","link":"https://swcdn.apple.com/content/downloads/56/26/031-46447/e9xjcfmv0t3t6nrw01zn99ez32brni5wd6/Safari9.1Mavericks.pkg","icon":"fas fa-download","type":"pkg","size":-1}]},{"title":"Devices","type":"grid","class":"smallTitle","content":[{"title":"Safari (macOS)","key":"Safari (macOS)","subtitle":"Jan 7, 2003","subgroups":[],"links":[],"img":"Safari (macOS)","imgFlags":{"internal":true,"dark":false},"icons":[],"link":"/device/identifier/Safari-(macOS)","singleDownload":{"text":"pkg (NaN undefined)","key":"Safari (macOS)","link":"https://swcdn.apple.com/content/downloads/56/26/031-46447/e9xjcfmv0t3t6nrw01zn99ez32brni5wd6/Safari9.1Mavericks.pkg","icon":"fas fa-download","type":"pkg","size":-1}}]}]}